README.md
setup.py
libspy/api.py
libspy.egg-info/PKG-INFO
libspy.egg-info/SOURCES.txt
libspy.egg-info/dependency_links.txt
libspy.egg-info/entry_points.txt
libspy.egg-info/requires.txt
libspy.egg-info/top_level.txt