Metadata-Version: 1.1
Name: libspy
Version: 0.0.1
Summary: A api and minimal server of ss
Home-page: https://github.com/zylo117/libspy
Author: carl cheung
Author-email: UNKNOWN
License: GNU General Public License version 3
Platform: UNKNOWN
Classifier: License :: OSI Approved :: Apache Software License
Classifier: Programming Language :: Python :: 3
Classifier: Topic :: Internet :: Proxy Servers
